{
  "headers": {
    "x-frame-options": "DENY",
    "via": "http/2 edgeproxy-h",
    "content-security-policy": "default-src 'none'; style-src 'unsafe-inline'; sandbox",
    "x-amz-cf-id": "a2jLY-_0XvATUSrn0PhkVCDL4DwfXMR2VZx8JxcpBZPvj8We6RDqSA==",
    "accept-ranges": "bytes",
    "referrer-policy": "strict-origin-when-cross-origin",
    "x-amz-cf-pop": "FRA56-P5",
    "x-amz-version-id": "7okrWff08vb4scSzK.WXMG1fzDDynI_T",
    "server": "deno/gcp-europe-west3",
    "server-timing": "fetchSource;dur=14",
    "last-modified": "Fri, 25 Mar 2022 13:32:50 GMT",
    "strict-transport-security": "max-age=63072000; includeSubDomains; preload",
    "cache-control": "public, max-age=31536000, immutable",
    "etag": "\"c1936f5c3f69d6ef25156cc15ff2dacc\"",
    "content-type": "application/typescript; charset=utf-8",
    "vary": "Accept-Encoding, Origin",
    "x-cache": "Hit from cloudfront",
    "age": "11859581",
    "cross-origin-opener-policy": "same-origin",
    "x-amz-replication-status": "COMPLETED",
    "content-length": "11317",
    "cross-origin-embedder-policy": "same-origin",
    "cross-origin-resource-policy": "same-origin",
    "x-content-type-options": "nosniff",
    "date": "Tue, 16 Jan 2024 06:30:33 GMT",
    "access-control-allow-origin": "*"
  },
  "url": "https://deno.land/std@0.132.0/node/os.ts",
  "now": {
    "secs_since_epoch": 1717246213,
    "nanos_since_epoch": 166346761
  }
}